<system>
    <name>WASP-138</name>
    <declination>-0 28 50</declination>
    <distance>308.0</distance>
    <rightascension>0 28 46</rightascension>
    <star>
        <name>WASP-138</name>
        <magV>11.81</magV>
        <mass>1.22</mass>
        <metallicity>-0.09</metallicity>
        <radius>1.36</radius>
        <spectraltype>F9</spectraltype>
        <temperature>6272.0</temperature>
        <planet>
            <name>WASP-138 b</name>
            <impactparameter>0.19</impactparameter>
            <inclination>88.5</inclination>
            <mass>1.22</mass>
            <period>3.634433</period>
            <semimajoraxis>0.0494</semimajoraxis>
        </planet>
    </star>
</system>

